{
    "title": "最新消息",
    "link": "https://phys.site.nthu.edu.tw/p/403-1335-3567-1.php?Lang=zh-tw",
    "language": "zh-tw",
    "department": "理學院物理學系",
    "articles": [
        {
            "title": "【招生公告】115學年度大學申請入學相關資訊公告",
            "link": "https://phys.site.nthu.edu.tw/p/406-1335-298257,r3567.php?Lang=zh-tw",
            "date": ""
        },
        {
            "title": "【博士生獎學金公告】114學年度(校級)各項博士生獎學金獲獎名單",
            "link": "https://phys.site.nthu.edu.tw/p/406-1335-298816,r3567.php?Lang=zh-tw",
            "date": ""
        },
        {
            "title": "【獎學金公告】2026年總統教育獎校內遴選(系截止：11/21)",
            "link": "https://phys.site.nthu.edu.tw/p/406-1335-298717,r3567.php?Lang=zh-tw",
            "date": ""
        },
        {
            "title": "【招生公告】115學年度特殊選才複試相關公告",
            "link": "https://phys.site.nthu.edu.tw/p/406-1335-298606,r3567.php?Lang=zh-tw",
            "date": ""
        },
        {
            "title": "【招生公告】115學年度博士班甄試初試審查結果",
            "link": "https://phys.site.nthu.edu.tw/p/450-1335-297856,c0.php?Lang=zh-tw",
            "date": ""
        }
    ]
}