{
    "title": "醫學系：新聞",
    "link": "https://med.site.nthu.edu.tw/p/403-1551-9676-1.php?Lang=zh-tw",
    "language": "zh-tw",
    "department": "生命科學暨醫學院學士後醫學系",
    "articles": [
        {
            "title": "本系王慧菁老師研究團隊參加「2025耳目醫新精準健康 Demo Day」全國生醫創新創業競賽拿到金獎",
            "link": "https://med.site.nthu.edu.tw/p/406-1551-298843,r9676.php?Lang=zh-tw",
            "date": ""
        },
        {
            "title": "114年08月16日白袍授袍典禮",
            "link": "https://med.site.nthu.edu.tw/p/406-1551-293897,r9676.php?Lang=zh-tw",
            "date": ""
        },
        {
            "title": "114年08月05日國民防疫醫學課程-參訪裕利股份有限公司",
            "link": "https://med.site.nthu.edu.tw/p/406-1551-293886,r9676.php?Lang=zh-tw",
            "date": ""
        },
        {
            "title": "114年07月28日新生開學上課日",
            "link": "https://med.site.nthu.edu.tw/p/406-1551-292979,r9676.php?Lang=zh-tw",
            "date": ""
        },
        {
            "title": "114年07月26日新生座談會活動",
            "link": "https://med.site.nthu.edu.tw/p/406-1551-292977,r9676.php?Lang=zh-tw",
            "date": ""
        },
        {
            "title": "114年06月12日113-2與系主任有約",
            "link": "https://med.site.nthu.edu.tw/p/406-1551-290794,r9676.php?Lang=zh-tw",
            "date": ""
        },
        {
            "title": "本系周宏學系主任榮獲2025年徐千田防癌研究基金會優秀論文獎",
            "link": "https://med.site.nthu.edu.tw/p/406-1551-287010,r9676.php?Lang=zh-tw",
            "date": ""
        },
        {
            "title": "114年3月20日生醫院舉辦院長榮譽榜頒獎典禮",
            "link": "https://med.site.nthu.edu.tw/p/406-1551-285886,r9676.php?Lang=zh-tw",
            "date": ""
        },
        {
            "title": "114年3月8日第二屆厚德醫學講座的活動成果",
            "link": "https://med.site.nthu.edu.tw/p/406-1551-285882,r9676.php?Lang=zh-tw",
            "date": ""
        },
        {
            "title": "社區與偏鄉醫療實務",
            "link": "https://med.site.nthu.edu.tw/p/406-1551-281675,r9676.php?Lang=zh-tw",
            "date": ""
        },
        {
            "title": "衛福部桃園醫院與清華大學簽MOU　培育醫學專才",
            "link": "https://med.site.nthu.edu.tw/p/406-1551-281541,r9676.php?Lang=zh-tw",
            "date": ""
        },
        {
            "title": "114年01月08日長庚醫院臨床醫學人文討論會CMHC",
            "link": "https://med.site.nthu.edu.tw/p/406-1551-281457,r9676.php?Lang=zh-tw",
            "date": ""
        }
    ]
}