{
    "title": "最新消息",
    "link": "https://pmed.site.nthu.edu.tw/p/403-1522-11-1.php?Lang=zh-tw",
    "language": "zh-tw",
    "department": "生命科學暨醫學院精準醫療博士學位學程",
    "articles": [
        {
            "title": "<公告>115學年度博士班甄試第二梯次放榜錄取名單 (含報到須知)",
            "link": "https://pmed.site.nthu.edu.tw/p/450-1522-298823,c0.php?Lang=zh-tw",
            "date": "2025-11-14"
        },
        {
            "title": "【公告】115學年度博士班甄試複試通知：114年11月8日(六) 精準醫療博士學位學程博士班甄試面試公告",
            "link": "https://pmed.site.nthu.edu.tw/p/406-1522-297809,r11.php?Lang=zh-tw",
            "date": "2025-10-31"
        },
        {
            "title": "114學年度第一次逕行修讀生醫學院精準醫療博士班學位學程作業公告",
            "link": "https://pmed.site.nthu.edu.tw/p/406-1522-295540,r11.php?Lang=zh-tw",
            "date": "2025-09-16"
        },
        {
            "title": "【公告】115學年度碩、博士班甄試 招生公告(含簡章下載)",
            "link": "https://pmed.site.nthu.edu.tw/p/450-1522-295364,c0.php?Lang=zh-tw",
            "date": "2025-09-12"
        },
        {
            "title": "＜公告>114學年度博士班考試入學第二次放榜錄取名單(含報到須知)",
            "link": "https://pmed.site.nthu.edu.tw/p/450-1522-288992,c0.php?Lang=zh-tw",
            "date": "2025-05-16"
        },
        {
            "title": "【公告】114學年度博士班考試入學複試通知：114年5月10日(六) 精準醫療博士學位學程博士班考試入學面試公告",
            "link": "https://pmed.site.nthu.edu.tw/p/406-1522-287989,r11.php?Lang=zh-tw",
            "date": "2025-05-02"
        },
        {
            "title": "【公告】114學年度轉系、所申請公告 （轉入）",
            "link": "https://pmed.site.nthu.edu.tw/p/406-1522-286104,r11.php?Lang=zh-tw",
            "date": "2025-04-30"
        },
        {
            "title": "【公告】114學年度博士班考試入學招生公告",
            "link": "https://pmed.site.nthu.edu.tw/p/406-1522-281731,r11.php?Lang=zh-tw",
            "date": "2025-01-21"
        },
        {
            "title": "＜公告＞113學年度第一次辦理逕行修讀博士學位核准名單",
            "link": "https://pmed.site.nthu.edu.tw/p/450-1522-279161,c0.php?Lang=zh-tw",
            "date": "2024-11-25"
        },
        {
            "title": "<公告>114學年度博士班甄試第二梯次放榜錄取名單 (含報到須知)",
            "link": "https://pmed.site.nthu.edu.tw/p/450-1522-278087,c0.php?Lang=zh-tw",
            "date": "2024-11-08"
        },
        {
            "title": "【公告】原訂11/2（六）上午 舉辦114學年度博士班甄試複試（口試），因颱風來襲，當天改採『線上視訊』方式舉行",
            "link": "https://pmed.site.nthu.edu.tw/p/406-1522-277504,r11.php?Lang=zh-tw",
            "date": "2024-10-29"
        },
        {
            "title": "【公告】114學年度博士班甄試複試通知：113年11月2日(六) 精準醫療博士學位學程博士班甄試面試公告",
            "link": "https://pmed.site.nthu.edu.tw/p/406-1522-277246,r11.php?Lang=zh-tw",
            "date": "2024-10-25"
        }
    ]
}