{
    "title": "最新公告",
    "link": "https://affairs.site.nthu.edu.tw/p/403-1165-127-1.php?Lang=zh-tw",
    "language": "zh-tw",
    "department": "總務處事務組",
    "articles": [
        {
            "title": "因應11/20(四)上午台積館進行空調設備吊掛作業，將設置台積館臨時公車站牌等候區",
            "link": "https://affairs.site.nthu.edu.tw/p/406-1165-298960,r127.php?Lang=zh-tw",
            "date": "2025-11-17"
        },
        {
            "title": "【徵才】國立清華大學總務處事務組誠徵約僱管理員1名",
            "link": "https://affairs.site.nthu.edu.tw/p/406-1165-298964,r127.php?Lang=zh-tw",
            "date": "2025-11-17"
        },
        {
            "title": "【徵才】清華大學總務處事務組誠徵專案組員1名",
            "link": "https://affairs.site.nthu.edu.tw/p/406-1165-298957,r127.php?Lang=zh-tw",
            "date": "2025-11-17"
        },
        {
            "title": "11/12(三)運動會停課一日，調整校園公車及南大校區區間車時刻表",
            "link": "https://affairs.site.nthu.edu.tw/p/406-1165-298502,r127.php?Lang=zh-tw",
            "date": "2025-11-10"
        },
        {
            "title": "《鳳凰颱風防颱通知 Typhoon Preparedness Notice》",
            "link": "https://affairs.site.nthu.edu.tw/p/406-1165-298500,r127.php?Lang=zh-tw",
            "date": "2025-11-10"
        },
        {
            "title": "校園流浪犬訊息 Campus Stray Dog Notice",
            "link": "https://affairs.site.nthu.edu.tw/p/406-1165-298135,r127.php?Lang=zh-tw",
            "date": "2025-11-04"
        },
        {
            "title": "【徵才】清華大學總務處事務組行政庶務工作誠徵職務代理人1名",
            "link": "https://affairs.site.nthu.edu.tw/p/406-1165-297789,r127.php?Lang=zh-tw",
            "date": "2025-10-29"
        },
        {
            "title": "11/3(一)~12/21(日)南大校區區間車時刻表",
            "link": "https://affairs.site.nthu.edu.tw/p/406-1165-297756,r127.php?Lang=zh-tw",
            "date": "2025-10-29"
        },
        {
            "title": "更新11/3(一)~12/20(六)校園公車時刻表",
            "link": "https://affairs.site.nthu.edu.tw/p/406-1165-297757,r127.php?Lang=zh-tw",
            "date": "2025-10-29"
        },
        {
            "title": "10/29(三)上午設置綜二館臨時公車站牌公告",
            "link": "https://affairs.site.nthu.edu.tw/p/406-1165-297687,r127.php?Lang=zh-tw",
            "date": "2025-10-28"
        },
        {
            "title": "光復節連續假期10月24日(五)~10月26日(日)校園公車及南大校區區間車停駛",
            "link": "https://affairs.site.nthu.edu.tw/p/406-1165-297264,r127.php?Lang=zh-tw",
            "date": "2025-10-17"
        },
        {
            "title": "114年10月24日(五)至10月26日(日) 光復節連假期間垃圾清運時間表",
            "link": "https://affairs.site.nthu.edu.tw/p/406-1165-297098,r127.php?Lang=zh-tw",
            "date": "2025-10-15"
        }
    ]
}