{
    "index": "4505",
    "name": "第三組",
    "parent_name": "人事室",
    "url": "https://tel.net.nthu.edu.tw/nthusearch/dept.php?dd=4505",
    "details": {
        "departments": [],
        "contact": {
            "分機": "31371",
            "直撥電話": "03-5731371",
            "傳真電話": "035722201"
        },
        "people": [
            {
                "姓　名": "范仁珠",
                "職稱/職責": "組長 / 督導三組相關法規之擬訂與修正、三組年度工作計 \r\n畫之擬訂",
                "分機": "34575",
                "備註": "N/A",
                "Email": "frju@mx.nthu.edu.tw"
            },
            {
                "姓　名": "羅佩文",
                "職稱/職責": "專員 / 學校約用人員及職務代理之任免、續聘、離職、\r\n資遣、升級(含職務津貼改支)等事宜；學校校聘人\r\n員、技工工友退撫相關業務",
                "分機": "31371",
                "備註": "N/A",
                "Email": "pwlo@mx.nthu.edu.tw"
            },
            {
                "姓　名": "彭子容",
                "職稱/職責": "組員 / 勞動基準法相關法規、教學單位專題計畫人員進\r\n用、核薪、待遇調整、年資晉薪、資遣案；主辦\r\n勞資會議及工友人評會；技工工友敘薪、薪資調\r\n整、年資晉薪、平時考核、年終考核及獎懲；約\r\n用(學校約用及專題)人員及技工工友之兼職、兼\r\n課案",
                "分機": "31378",
                "備註": "N/A",
                "Email": "pengtj@mx.nthu.edu.tw"
            },
            {
                "姓　名": "池奕璇",
                "職稱/職責": "組員 / 行政單位及校控專題計畫人員進用、核薪、待遇調 \r\n整、年資晉薪、資遣案/學校約人員、專題計畫人員 \r\n及技工工友年終工作獎金/社員退費事宜",
                "分機": "34568",
                "備註": "N/A",
                "Email": "chi@mx.nthu.edu.tw"
            },
            {
                "姓　名": "魏士巽",
                "職稱/職責": "職務代理人 / 外籍人士離職儲金核發；辦理績優技工工\r\n友選拔；國內出差旅費案件審核；清華附小及實驗中\r\n學(小學)入學、轉學案；緩召、逐召申請案；校聘人\r\n員及技工工友職名章製發及服務、在職、離職證明核\r\n發、 績效酬勞審核",
                "分機": "31317",
                "備註": "N/A",
                "Email": "sswei@mx.nthu.edu.tw"
            },
            {
                "姓　名": "孫藝瑀",
                "職稱/職責": "行政組員 / 專任人員之勞健保及勞退加/退保申報；勞\r\n健保及勞退個人負擔；勞健保及勞退雇主負擔",
                "分機": "31322",
                "備註": "N/A",
                "Email": "sun2@mx.nthu.edu.tw"
            },
            {
                "姓　名": "吳佩伃",
                "職稱/職責": "行政組員 / 兼任教師、學生兼任助理、臨時工及不適用\r\n勞基法人員之勞健保及勞退加/退保申報；勞健保及勞\r\n退個人負擔；勞健保及勞退雇主負擔；加班及未休工\r\n資審核；職災、勞保給付等申報業務",
                "分機": "31312",
                "備註": "N/A",
                "Email": "py.wu@mx.nthu.edu.tw"
            },
            {
                "姓　名": "曾逸姍",
                "職稱/職責": "研究助理 / 本室資訊系統窗口",
                "分機": "35317",
                "備註": "N/A",
                "Email": "yishan_tseng@mx.nthu.edu.tw"
            },
            {
                "姓　名": "魏郁純",
                "職稱/職責": "助理員 / 教職員工留職停薪及回職復薪、育嬰留職停薪申報 \r\n及育嬰津貼申辦；延長病假核算與審核；差勤系統\r\n維護；差勤紙本請假及扣薪",
                "分機": "33156",
                "備註": "N/A",
                "Email": "yuchunwei@mx.nthu.edu.tw"
            },
            {
                "姓　名": "陳㛄婷",
                "職稱/職責": "職務代理人 / 兼任助理及獎助生專案業務及窗口；赴大陸申請；辦\r\n理校長因公出國案；派遣/承攬人力資料彙整報送及相\r\n關公文簽辦",
                "分機": "34570",
                "備註": "N/A",
                "Email": "chenyiting@mx.nthu.edu.tw"
            }
        ]
    }
}