{
    "title": "News",
    "link": "https://bai.site.nthu.edu.tw/p/403-1523-11-1.php?Lang=en",
    "language": "en",
    "department": "教務處智慧生醫博士學位學程",
    "articles": [
        {
            "title": "114th Academic Year – First Direct Admission to the Ph.D. Program in Intelligent Biomedical Science (Deadline: November 14)/114學年度第一次逕行修讀教務處智慧生醫博士學位學程作業公告(11/14截止)",
            "link": "https://bai.site.nthu.edu.tw/p/406-1523-298784,r11.php?Lang=en",
            "date": ""
        },
        {
            "title": "114th Academic Year Biomedical AI PhD Program Entrance Examination: Program Your Future Contributions to Biomedical Science",
            "link": "https://bai.site.nthu.edu.tw/p/406-1523-285830,r11.php?Lang=en",
            "date": ""
        },
        {
            "title": "114th Academic Year Biomedical AI PhD Program Entrance Examination: Biomedical Experts, Leading the Future with AI",
            "link": "https://bai.site.nthu.edu.tw/p/406-1523-285831,r11.php?Lang=en",
            "date": ""
        },
        {
            "title": "(New Student Enrollment)2024 Fall semester Student Registration Procedures & Guidelines(for Foreign Students)",
            "link": "https://bai.site.nthu.edu.tw/p/450-1523-272173,c0.php?Lang=en",
            "date": ""
        },
        {
            "title": "(Congratulations)Prof. Chi-Chun Lee received the 2023 NSTC Outstanding Research Award.",
            "link": "https://bai.site.nthu.edu.tw/p/450-1523-263955,c0.php?Lang=en",
            "date": ""
        },
        {
            "title": "(Congratulations) Prof. (joint appointment) Zong-Hong Lin received the 2023 NSTC Outstanding Research Award.",
            "link": "https://bai.site.nthu.edu.tw/p/450-1523-263958,c0.php?Lang=en",
            "date": ""
        }
    ]
}