{
    "title": "最新消息",
    "link": "https://cashier.site.nthu.edu.tw/p/403-1166-47-1.php?Lang=zh-tw",
    "language": "zh-tw",
    "department": "總務處出納組",
    "articles": [
        {
            "title": "114學年度第1學期學分費繳費公告",
            "link": "https://cashier.site.nthu.edu.tw/p/406-1166-295176,r47.php?Lang=zh-tw",
            "date": "2025-09-10"
        },
        {
            "title": "兆豐銀行114年教師節薪資轉帳戶專案獻禮",
            "link": "https://cashier.site.nthu.edu.tw/p/406-1166-294542,r47.php?Lang=zh-tw",
            "date": "2025-09-01"
        },
        {
            "title": "玉山銀行114年教師節薪資轉帳戶專案獻禮",
            "link": "https://cashier.site.nthu.edu.tw/p/406-1166-294543,r47.php?Lang=zh-tw",
            "date": "2025-09-01"
        },
        {
            "title": "「申請開立收據-已匯入款」系統於114年9月1日上線使用 (捐款不適用此系統)",
            "link": "https://cashier.site.nthu.edu.tw/p/406-1166-294438,r47.php?Lang=zh-tw",
            "date": "2025-08-29"
        },
        {
            "title": "8/20(三)南大校區下午停電通知。南大校區出納組現金繳納收費時間改為上午8:30~11:30。",
            "link": "https://cashier.site.nthu.edu.tw/p/406-1166-293666,r47.php?Lang=zh-tw",
            "date": "2025-08-13"
        },
        {
            "title": "114學年度第1學期學雜費繳費公告",
            "link": "https://cashier.site.nthu.edu.tw/p/406-1166-292553,r47.php?Lang=zh-tw",
            "date": "2025-07-21"
        },
        {
            "title": "兆豐銀行滿意度調查(延長至114.06.04)",
            "link": "https://cashier.site.nthu.edu.tw/p/406-1166-289058,r47.php?Lang=zh-tw",
            "date": "2025-05-19"
        },
        {
            "title": "「轉知」國稅局宣導113年度個人綜合所得稅申報事宜",
            "link": "https://cashier.site.nthu.edu.tw/p/406-1166-288340,r47.php?Lang=zh-tw",
            "date": "2025-05-08"
        },
        {
            "title": "本校駐點銀行114年5月1日(四)休假公告",
            "link": "https://cashier.site.nthu.edu.tw/p/406-1166-287713,r47.php?Lang=zh-tw",
            "date": "2025-04-28"
        },
        {
            "title": "113年度各類所得扣繳憑單請至校務資訊系統查看或至出納組申請",
            "link": "https://cashier.site.nthu.edu.tw/p/406-1166-286944,r47.php?Lang=zh-tw",
            "date": "2025-04-15"
        },
        {
            "title": "【轉知】兆豐銀行訂於114/3/28(星期五)於風雲樓ATM旁增設補摺機作業公告。",
            "link": "https://cashier.site.nthu.edu.tw/p/406-1166-286006,r47.php?Lang=zh-tw",
            "date": "2025-03-27"
        },
        {
            "title": "113學年度第2學期學分費繳費公告",
            "link": "https://cashier.site.nthu.edu.tw/p/406-1166-284214,r47.php?Lang=zh-tw",
            "date": "2025-03-04"
        }
    ]
}